{
  "required": true,
  "package": "team.teampotato.ruok.forge.mixins",
  "compatibilityLevel": "JAVA_17",
  "minVersion": "0.8",
  "client": [
    "Minecraft.Accessor.MinecraftClientAccessor",
    "Minecraft.Gui.ChatHudMixin",
    "Minecraft.Invoker.WorldRendererInvoker",
    "Minecraft.Render.World.LightingProviderMixin",
    "Minecraft.Render.World.ClientPlayNetworkHandlerMixin",
    "Minecraft.Render.World.ClientWorldMixin",
    "Minecraft.Render.World.EntityRenderDispatcherMixin",
    "Minecraft.Render.World.ExplosionEmitterParticleMixin",
    "Minecraft.Render.World.ExplosionS2CPacketMixin",
    "Minecraft.Render.World.ItemEntityRendererMixin",
    "Minecraft.Render.World.LightTextureMixin",
    "Minecraft.Render.World.TntMinecartEntityRendererMixin",
    "Sodium.SodiumGUIMixin"
  ],
  "mixins": [
  ],
  "injectors": {
    "defaultRequire": 1
  }
}